odoo/addons/sale_outgoing_product/README.rst
odoo/addons/sale_outgoing_product/__init__.py
odoo/addons/sale_outgoing_product/__manifest__.py
odoo/addons/sale_outgoing_product/i18n/de.po
odoo/addons/sale_outgoing_product/i18n/it.po
odoo/addons/sale_outgoing_product/i18n/sale_outgoing_product.pot
odoo/addons/sale_outgoing_product/readme/CONTRIBUTORS.rst
odoo/addons/sale_outgoing_product/readme/DESCRIPTION.rst
odoo/addons/sale_outgoing_product/readme/USAGE.rst
odoo/addons/sale_outgoing_product/static/description/icon.png
odoo/addons/sale_outgoing_product/static/description/index.html
odoo/addons/sale_outgoing_product/views/stock_move_views.xml
odoo14_addon_sale_outgoing_product-14.0.1.0.1.dev6.dist-info/METADATA
odoo14_addon_sale_outgoing_product-14.0.1.0.1.dev6.dist-info/WHEEL
odoo14_addon_sale_outgoing_product-14.0.1.0.1.dev6.dist-info/top_level.txt
odoo14_addon_sale_outgoing_product-14.0.1.0.1.dev6.dist-info/RECORD
